LICENSE
MANIFEST.in
README.md
setup.cfg
setup.py
ilms/__init__.py
ilms/cli.py
ilms/core.py
ilms/exception.py
ilms/parser.py
ilms/route.py
ilms/utils.py
ilms_nthu.egg-info/PKG-INFO
ilms_nthu.egg-info/SOURCES.txt
ilms_nthu.egg-info/dependency_links.txt
ilms_nthu.egg-info/entry_points.txt
ilms_nthu.egg-info/requires.txt
ilms_nthu.egg-info/top_level.txt