Metadata-Version: 1.1
Name: ilms-nthu
Version: 0.2.5
Summary: iLms-NTHU API. An iLMS client for students, assistants and developers.
Home-page: https://github.com/leVirve/iLms-nthu-API
Author: leVirve
Author-email: gae.m.project@gmail.com
License: MIT
Keywords: iLms,NTHU,API
Platform: any
Classifier: Development Status :: 3 - Alpha
Classifier: Intended Audience :: Developers
Classifier: Intended Audience :: Customer Service
Classifier: Intended Audience :: System Administrators
Classifier: Topic :: Internet :: WWW/HTTP
Classifier: Topic :: Software Development :: Libraries
Classifier: Topic :: Text Processing
Classifier: Topic :: Utilities
Classifier: Programming Language :: Python
Classifier: Programming Language :: Python :: 3.5
Classifier: Programming Language :: Python :: 3.6
